deepneighbor/__init__.py
deepneighbor/config.py
deepneighbor/data.py
deepneighbor/embed.py
deepneighbor/main.py
deepneighbor/utils.py
deepneighbor/walker.py
deepneighbor/models/__init__.py
deepneighbor/models/deepwalk.py
deepneighbor/models/embed.py
deepneighbor/models/gat.py
deepneighbor/models/gcn.py
deepneighbor/models/param_parser.py
deepneighbor/models/utils.py
deepneighbor-0.3.1.dist-info/LICENSE
deepneighbor-0.3.1.dist-info/METADATA
deepneighbor-0.3.1.dist-info/WHEEL
deepneighbor-0.3.1.dist-info/top_level.txt
deepneighbor-0.3.1.dist-info/RECORD
