Metadata-Version: 2.1
Name: deepneighbor
Version: 0.3.1
Summary: embedding-based item nearest neighborhoods extraction
Home-page: https://github.com/LouisBIGDATA/deepneighbor
Author: Yufeng Wang
Author-email: louiswang524@gmail.com
License: UNKNOWN
Keywords: embedding,information retrieval,deep learning,torch,tensor,pytorch,nearest neighbor
Platform: UNKNOWN
Classifier: Programming Language :: Python :: 3
Classifier: License :: OSI Approved :: MIT License
Classifier: Operating System :: OS Independent
Classifier: Intended Audience :: Developers
Classifier: Intended Audience :: Education
Classifier: Intended Audience :: Science/Research
Classifier: Topic :: Scientific/Engineering
Classifier: Topic :: Scientific/Engineering :: Artificial Intelligence
Classifier: Topic :: Software Development
Classifier: Topic :: Software Development :: Libraries
Classifier: Topic :: Software Development :: Libraries :: Python Modules
Requires-Python: >=3.4
Requires-Dist: h5py
Requires-Dist: requests
Requires-Dist: gensim (==3.7.0)
Requires-Dist: tqdm
Requires-Dist: numpy
Requires-Dist: scikit-learn
Requires-Dist: pandas
Requires-Dist: annoy
Requires-Dist: dgl
Requires-Dist: torch (>=1.1.0)
